swampyer-3.0.20241129.dist-info/METADATA
swampyer-3.0.20241129.dist-info/WHEEL
swampyer-3.0.20241129.dist-info/entry_points.txt
swampyer-3.0.20241129.dist-info/licenses/LICENCE.txt
swampyer/__init__.py
swampyer/client.py
swampyer/common.py
swampyer/exceptions.py
swampyer/fields.py
swampyer/messages.py
swampyer/queues.py
swampyer/serializers.py
swampyer/transport.py
swampyer/utils.py
swampyer-3.0.20241129.dist-info/RECORD
